{
  "target_col": "target_direction",
  "selected_features": [
    "roc_20",
    "rolling_var_5",
    "month_sin",
    "macd",
    "volume_lag_5",
    "return_lag_10",
    "rolling_vol_10",
    "volume_lag_20",
    "rolling_vol_5",
    "dist_sma_5",
    "volume_ratio_5",
    "day_of_week_sin",
    "momentum_20",
    "return_lag_5",
    "dist_sma_50",
    "day_of_week",
    "roc_10",
    "price_diff",
    "atr_pct",
    "dist_sma_10",
    "volume_change",
    "rolling_var_20",
    "momentum_10",
    "open_close_diff",
    "volume_ratio_10",
    "Volume",
    "dist_sma_20",
    "volume_ratio_20",
    "return_lag_1",
    "dist_sma_100",
    "volume_momentum",
    "return_lag_3",
    "volume_lag_10",
    "price_diff_pct",
    "volume_lag_1",
    "obv",
    "bb_width",
    "macd_hist",
    "rolling_var_10",
    "dist_sma_200"
  ],
  "target_columns": [
    "target_next_close",
    "target_next_return",
    "target_return_5d",
    "target_direction",
    "target_signal"
  ],
  "dropped": {
    "low_variance": [
      "vol_std_20"
    ],
    "redundant": [
      "Adj Close",
      "Close",
      "Low",
      "Open",
      "bb_lower",
      "bb_mid",
      "bb_upper",
      "close_lag_1",
      "close_lag_10",
      "close_lag_20",
      "close_lag_3",
      "close_lag_5",
      "daily_return",
      "day_of_week_cos",
      "dist_ema_10",
      "dist_ema_20",
      "dist_ema_5",
      "dist_ema_50",
      "ema_10",
      "ema_20",
      "ema_5",
      "ema_50",
      "hist_vol_21",
      "log_return",
      "macd_signal",
      "month",
      "open_lag_1",
      "open_lag_10",
      "open_lag_20",
      "open_lag_3",
      "open_lag_5",
      "pct_change_1d",
      "quarter",
      "rolling_max_10",
      "rolling_max_20",
      "rolling_max_5",
      "rolling_mean_10",
      "rolling_mean_20",
      "rolling_mean_5",
      "rolling_median_10",
      "rolling_median_20",
      "rolling_median_5",
      "rolling_min_10",
      "rolling_min_20",
      "rolling_min_5",
      "sma_10",
      "sma_100",
      "sma_20",
      "sma_200",
      "sma_5",
      "sma_50",
      "trading_day_number",
      "typical_price",
      "vol_ann_20",
      "vol_std_20",
      "weighted_close",
      "year"
    ],
    "below_rank": [
      "return_lag_20",
      "volume_change_ratio",
      "roc_5",
      "high_low_range",
      "vma_20",
      "volume_lag_3",
      "bb_pct",
      "vma_5",
      "vma_10",
      "momentum_5",
      "atr",
      "rsi",
      "day_of_month",
      "rolling_vol_20",
      "High",
      "week",
      "month_cos"
    ]
  },
  "scores": {
    "High": {
      "mutual_info": 0.0,
      "tree_importance": 0.012210937867109983,
      "variance": 30814.212230956593
    },
    "Volume": {
      "mutual_info": 0.0026830405800777335,
      "tree_importance": 0.019291668409263156,
      "variance": 157371808145416.88
    },
    "price_diff": {
      "mutual_info": 0.005671585433078441,
      "tree_importance": 0.018699182072179115,
      "variance": 13.022858462946605
    },
    "price_diff_pct": {
      "mutual_info": 0.0,
      "tree_importance": 0.025612949331052487,
      "variance": 0.00035250116932498325
    },
    "high_low_range": {
      "mutual_info": 0.0,
      "tree_importance": 0.017323395926194092,
      "variance": 0.0004020375019170226
    },
    "open_close_diff": {
      "mutual_info": 0.002925268877076892,
      "tree_importance": 0.020828829163297362,
      "variance": 0.0003203848720579293
    },
    "dist_sma_5": {
      "mutual_info": 0.008647300966265536,
      "tree_importance": 0.019559248976751095,
      "variance": 0.0004221518638725571
    },
    "dist_sma_10": {
      "mutual_info": 0.004959423447454814,
      "tree_importance": 0.018104446181323862,
      "variance": 0.000889516307420756
    },
    "dist_sma_20": {
      "mutual_info": 0.0020496036088895053,
      "tree_importance": 0.01694669711395676,
      "variance": 0.0018483981603285658
    },
    "dist_sma_50": {
      "mutual_info": 0.006551152270861893,
      "tree_importance": 0.026943877029704237,
      "variance": 0.004765804008529142
    },
    "dist_sma_100": {
      "mutual_info": 0.001270816229184124,
      "tree_importance": 0.01698491315953583,
      "variance": 0.00859562856566098
    },
    "dist_sma_200": {
      "mutual_info": 0.0,
      "tree_importance": 0.018821841372631178,
      "variance": 0.015098351485069227
    },
    "rsi": {
      "mutual_info": 0.0,
      "tree_importance": 0.013031755126773589,
      "variance": 260.0903173443851
    },
    "macd": {
      "mutual_info": 0.011335421301453374,
      "tree_importance": 0.02077558852454916,
      "variance": 17.567462490282818
    },
    "macd_hist": {
      "mutual_info": 0.0,
      "tree_importance": 0.019328392080775355,
      "variance": 1.355361071902385
    },
    "roc_5": {
      "mutual_info": 0.0,
      "tree_importance": 0.01748597637825385,
      "variance": 0.0016723116267426611
    },
    "roc_10": {
      "mutual_info": 0.005873720886153455,
      "tree_importance": 0.017795030999498012,
      "variance": 0.002960958100466597
    },
    "roc_20": {
      "mutual_info": 0.018287175587157645,
      "tree_importance": 0.01681274891270839,
      "variance": 0.006043341287641917
    },
    "momentum_5": {
      "mutual_info": 0.0,
      "tree_importance": 0.014140343904556202,
      "variance": 60.024089669726784
    },
    "momentum_10": {
      "mutual_info": 0.003434127365755657,
      "tree_importance": 0.01599622149257745,
      "variance": 123.85034581219985
    },
    "momentum_20": {
      "mutual_info": 0.006759578715097803,
      "tree_importance": 0.01670931457005039,
      "variance": 263.56511723382334
    },
    "atr": {
      "mutual_info": 0.0,
      "tree_importance": 0.01401081182839494,
      "variance": 15.362631092484646
    },
    "atr_pct": {
      "mutual_info": 0.005581250386708536,
      "tree_importance": 0.016647566326859296,
      "variance": 0.00025172122081361126
    },
    "bb_width": {
      "mutual_info": 0.0,
      "tree_importance": 0.02028988958996545,
      "variance": 0.005008632705440576
    },
    "bb_pct": {
      "mutual_info": 0.0,
      "tree_importance": 0.015481711777272464,
      "variance": 0.10262020764655218
    },
    "volume_change": {
      "mutual_info": 0.004537855609280328,
      "tree_importance": 0.023505819578897448,
      "variance": 165902987018217.9
    },
    "volume_change_ratio": {
      "mutual_info": 0.0,
      "tree_importance": 0.017910652350167484,
      "variance": 39.52696502904348
    },
    "vma_5": {
      "mutual_info": 0.0,
      "tree_importance": 0.014798791101638075,
      "variance": 87937927398215.17
    },
    "volume_ratio_5": {
      "mutual_info": 0.008276166240570593,
      "tree_importance": 0.016885995710854054,
      "variance": 0.15426211921295338
    },
    "vma_10": {
      "mutual_info": 0.0,
      "tree_importance": 0.014677538603952874,
      "variance": 74834255387010.38
    },
    "volume_ratio_10": {
      "mutual_info": 0.0027270819486766573,
      "tree_importance": 0.025300037812564423,
      "variance": 0.2458348050314717
    },
    "vma_20": {
      "mutual_info": 0.0,
      "tree_importance": 0.017059974619072084,
      "variance": 65247542129668.43
    },
    "volume_ratio_20": {
      "mutual_info": 0.0019072019501151782,
      "tree_importance": 0.024319697909225717,
      "variance": 0.33041625399976216
    },
    "obv": {
      "mutual_info": 0.0,
      "tree_importance": 0.022318310530322547,
      "variance": 9.204401180626492e+17
    },
    "volume_momentum": {
      "mutual_info": 0.0008321241511757282,
      "tree_importance": 0.021214392538831662,
      "variance": 0.08419772468963786
    },
    "week": {
      "mutual_info": 0.0,
      "tree_importance": 0.009356489696846361,
      "variance": 230.68260412596263
    },
    "day_of_week": {
      "mutual_info": 0.006045590727929762,
      "tree_importance": 0.004556637746444767,
      "variance": 1.9957613329530455
    },
    "day_of_month": {
      "mutual_info": 0.0,
      "tree_importance": 0.012718199026278396,
      "variance": 76.84934356259117
    },
    "month_sin": {
      "mutual_info": 0.01330199167074042,
      "tree_importance": 0.005941687327273948,
      "variance": 0.4919714956815218
    },
    "month_cos": {
      "mutual_info": 0.0,
      "tree_importance": 0.0034189076299280217,
      "variance": 0.5082151445711868
    },
    "day_of_week_sin": {
      "mutual_info": 0.007292975582932515,
      "tree_importance": 0.0034649909735751812,
      "variance": 0.26376388891986013
    },
    "volume_lag_1": {
      "mutual_info": 0.0,
      "tree_importance": 0.022366627346765235,
      "variance": 159962561206939.72
    },
    "return_lag_1": {
      "mutual_info": 0.001334397000703591,
      "tree_importance": 0.020804188871934876,
      "variance": 0.0003523920094723868
    },
    "volume_lag_3": {
      "mutual_info": 0.0,
      "tree_importance": 0.016470531636641764,
      "variance": 159479336111724.47
    },
    "return_lag_3": {
      "mutual_info": 0.0005958260367464607,
      "tree_importance": 0.019751879268474704,
      "variance": 0.0003518101221572349
    },
    "volume_lag_5": {
      "mutual_info": 0.010216337133930997,
      "tree_importance": 0.020004805823528805,
      "variance": 158808692833652.12
    },
    "return_lag_5": {
      "mutual_info": 0.006648953332392793,
      "tree_importance": 0.024724512940383022,
      "variance": 0.00035149561631717694
    },
    "volume_lag_10": {
      "mutual_info": 0.0,
      "tree_importance": 0.028077404687189923,
      "variance": 156740038731099.1
    },
    "return_lag_10": {
      "mutual_info": 0.009920637570194346,
      "tree_importance": 0.01629328010030616,
      "variance": 0.00035159146580389334
    },
    "volume_lag_20": {
      "mutual_info": 0.009255333021778833,
      "tree_importance": 0.024439119196505436,
      "variance": 153574362478399.06
    },
    "return_lag_20": {
      "mutual_info": 0.0,
      "tree_importance": 0.0187085352793528,
      "variance": 0.00034236851189615774
    },
    "rolling_var_5": {
      "mutual_info": 0.014512014980455401,
      "tree_importance": 0.01886595119673933,
      "variance": 4349.563235418499
    },
    "rolling_vol_5": {
      "mutual_info": 0.008752951432464018,
      "tree_importance": 0.01757230987829935,
      "variance": 0.0297706102597174
    },
    "rolling_var_10": {
      "mutual_info": 0.0,
      "tree_importance": 0.018827683369186585,
      "variance": 14471.920241520651
    },
    "rolling_vol_10": {
      "mutual_info": 0.009651208278762535,
      "tree_importance": 0.01883670794055759,
      "variance": 0.024722835746299885
    },
    "rolling_var_20": {
      "mutual_info": 0.0037747346088239375,
      "tree_importance": 0.014325437080388503,
      "variance": 57895.162237776894
    },
    "rolling_vol_20": {
      "mutual_info": 0.0,
      "tree_importance": 0.012649564112639192,
      "variance": 0.021165631892032768
    }
  },
  "split": {
    "total_rows": 5099,
    "train_rows": 3569,
    "val_rows": 764,
    "test_rows": 764,
    "train_end": "2020-04-27",
    "val_start": "2020-04-29",
    "val_end": "2023-05-24",
    "test_start": "2023-05-26",
    "test_end": "2026-07-03",
    "gap_days": 1,
    "method": "chronological"
  },
  "scaler": {
    "method": "standard",
    "columns": [
      "roc_20",
      "rolling_var_5",
      "month_sin",
      "macd",
      "volume_lag_5",
      "return_lag_10",
      "rolling_vol_10",
      "volume_lag_20",
      "rolling_vol_5",
      "dist_sma_5",
      "volume_ratio_5",
      "day_of_week_sin",
      "momentum_20",
      "return_lag_5",
      "dist_sma_50",
      "day_of_week",
      "roc_10",
      "price_diff",
      "atr_pct",
      "dist_sma_10",
      "volume_change",
      "rolling_var_20",
      "momentum_10",
      "open_close_diff",
      "volume_ratio_10",
      "Volume",
      "dist_sma_20",
      "volume_ratio_20",
      "return_lag_1",
      "dist_sma_100",
      "volume_momentum",
      "return_lag_3",
      "volume_lag_10",
      "price_diff_pct",
      "volume_lag_1",
      "obv",
      "bb_width",
      "macd_hist",
      "rolling_var_10",
      "dist_sma_200"
    ],
    "mean_": [
      0.017787467974201537,
      8.78546115481653,
      0.006389422128689642,
      0.9510276255268346,
      12706486.296665732,
      0.0007462910718871336,
      0.254340757034826,
      12563694.182191089,
      0.24343201517713783,
      0.0015955783497169193,
      1.001850724426729,
      0.35450000227821876,
      2.634495624938776,
      0.0007397063882025523,
      0.019917796309538334,
      1.9935556178201177,
      0.009141803369592626,
      0.12934434909451836,
      0.02749474402417235,
      0.0036862573815816305,
      -40066.961344914365,
      30.08878237924488,
      1.303581182768981,
      6.900479536279809e-05,
      1.002207143371295,
      12736399.202801906,
      0.007653208307329413,
      0.9977218979743322,
      0.0007661434017165488,
      0.04196051084065132,
      1.0026111153661725,
      0.000756284446739921,
      12656618.836402355,
      0.0008950667925435803,
      12780492.34813113,
      1850312241.9917064,
      0.11119399108204034,
      -0.01905466638168241,
      15.442309939716429,
      0.08880096421489196
    ],
    "scale_": [
      0.07422255603490785,
      19.651112614982953,
      0.7013085269178027,
      3.044898151857738,
      10022352.657568041,
      0.017125707270998672,
      0.1515895972726668,
      9744931.752209954,
      0.16455746999135268,
      0.01911647482685743,
      0.36966146112485304,
      0.5133248002908041,
      11.665565598895792,
      0.01712290717358954,
      0.06564643614351066,
      1.4113231184179889,
      0.050991989422261304,
      2.6952504382003095,
      0.01537867986708939,
      0.027681694974358895,
      7264439.244100375,
      70.116528715253,
      8.168467842817297,
      0.01624136085170854,
      0.43823711542962795,
      10022885.03679343,
      0.04056662673193635,
      0.4668940662941013,
      0.017149064129574388,
      0.08904867279711448,
      0.2681794253970702,
      0.017132091559885265,
      9921630.32885969,
      0.017161669709934508,
      10082164.007233936,
      958418500.6822959,
      0.067376501004477,
      0.8389659141592134,
      31.823469436558934,
      0.12042314055474376
    ]
  },
  "n_features_before": 114,
  "n_features_after": 40
}